Action.py
Game.py
RLObject.py
Replayer.py
console_colors.py
constants.py
rockalyzer.py
rockalyzer-0.1.0.dist-info/LICENSE
rockalyzer-0.1.0.dist-info/METADATA
rockalyzer-0.1.0.dist-info/WHEEL
rockalyzer-0.1.0.dist-info/top_level.txt
rockalyzer-0.1.0.dist-info/RECORD
