Metadata-Version: 2.1
Name: rockalyzer
Version: 0.1.0
Summary: Rocket League Boxcars-Replay Analyzer
Home-page: https://github.com/eliastheis/rockalyzer
Author: Elias Theis
Author-email: mail@eliastheis.de
Classifier: Programming Language :: Python :: 3
Classifier: Programming Language :: Python :: 3.7
Classifier: Programming Language :: Python :: 3.8
Classifier: Programming Language :: Python :: 3.9
Classifier: Programming Language :: Python :: 3.10
Classifier: Programming Language :: Python :: 3.11
Classifier: License :: OSI Approved :: MIT License
Classifier: Operating System :: OS Independent
License-File: LICENSE
Requires-Dist: numpy
Requires-Dist: matplotlib
